<?xml version="1.0" encoding="utf-8"?>
<openerp>
    <data>

        <record id="l10npt_invoice_inherit" model="ir.ui.view">
            <field name="name">account.invoice.l10npt.inherit</field>
            <field name="model">account.invoice</field>
            <field name="inherit_id" ref="account.invoice_form"/>
            <field name="arch" type="xml">
                <button name="invoice_cancel" position="replace">
                    <button name="invoice_cancel" states="draft,proforma2" string="Cancel" icon="gtk-cancel"/>
                </button>
            </field>
        </record>
    </data>
</openerp>
                                
